[
  {
    "start": "2026-06-13T13:00:00",
    "end": "2026-06-13T14:46:00",
    "resourceId": "viff-centre-viff-cinema",
    "title": "<div class=\"c-calendar-instance__container\">\n    <div class=\"c-calendar-instance c-calendar-instance__film\">\n        <button class=\"c-calendar-instance__toggle\" id=\"c-calendar-instance__toggle-49545\" aria-controls=\"c-calendar-instance__info-49545\" aria-label=\"Find out More\"><span class=\"u-hidden-visually\">Find out More</span></button>\n        <div class=\"c-calendar-instance__content\">\n\n            <div data-tooltip >\n                <button class=\"c-calendar-instance__favourite instance\" data-eventid=\"49520\" data-instanceid=\"49545\" data-tooltip-trigger data-tooltip-content=\"Add to Schedule\" aria-label=\"Favourite Alipato At Muog (Flying Embers & A Fortress)\">\n                    <i class=\"far fa-plus\" aria-hidden=\"true\"></i>\n                    <span class=\"u-hidden-visually\">Favourite Alipato At Muog (Flying Embers & A Fortress)</span>\n                </button>\n            </div>\n\n            <h3 class=\"c-calendar-instance__title\">\n                Alipato At Muog (Flying Embers & A Fortress)            </h3>\n            <p class=\"c-calendar-instance__time\">\n                <time datetime=\"2026-06-13T13:00:00-07:00\">\n                    1:00 pm                </time>\n                                    <span class=\"c-calendar-instance__duration\"><span class=\"fal fa-clock\" aria-hidden=\"true\"></span> 106 min</span>\n                            </p>\n            <div class=\"c-calendar-instance__info\" id=\"c-calendar-instance__info-49545\" role=\"region\" aria-labelledby=\"c-calendar-instance__toggle-49545\">\n                                    <p class=\"c-calendar-instance__type\">Film</p>\n                                                    Burgos' impassioned documentary about the military abduction of his brother Jonas, an activist and organizer, and the subsequent cover-up, recently became only the second doc to win the Filipino Academy Award for Best Film.                \n                                    <div class=\"c-calendar-instance__buttons\">\n                                                                        <a class=\"c-event-instance__btn c-btn--small  c-btn c-btn--primary\" href=\"https://viff.org/whats-on/alipato-at-muog/book/3VrToYvX1a\">\n                                Book Now                            </a>\n                                                                <a class=\"c-event-instance__btn c-btn--small  c-btn c-btn--ghost\" href=\"https://viff.org/whats-on/alipato-at-muog/\">\n                        More Info\n                    </a>\n                    </div>\n                            </div>\n        </div>\n    </div>\n</div>\n",
    "moreInfo": "<p>Initially censored with an X-rating in its home country, <em>Alipato at Muog (Flying Embers and a Fortress)</em>, lives up to its national rating board\u2019s determination that it &#8220;undermine[s] the faith and confidence of the people in their government and/or duly-constituted authorities.&#8221;</p>\n<p>Burgos\u2019 impassioned documentary about his family\u2019s almost 20 year search for his brother Jonas, an organizer of peasant farmers who was abducted by state forces at a shopping mall in broad daylight in 2007, clarifies the irredeemable nature of the current system of Philippine government through a headstrong and wholehearted cinematic expression of love and rage.</p>\n<p>Burgos and his close-knit team recently managed to win the country\u2019s highest national film awards, becoming only the second documentary to be recognized as the Best Film of the year by the Filipino Academy.</p>\n<p>According to human rights group Karapatan, a total of 1,915 individuals have been documented as desaparecidos or victims of enforced disappearance from the martial law era under Ferdinand Marcos Sr. to the current administration of his son and namesake.</p>\n<blockquote><p>One of the most important national portraits of the decade.</p>\n<p><strong>Sinegang.ph, Best Filipino Films of 2024</strong></p></blockquote>\n",
    "eventType": "Film"
  },
  {
    "start": "2026-06-14T13:30:00",
    "end": "2026-06-14T15:16:00",
    "resourceId": "viff-centre-lochmaddy-studio-theatre",
    "title": "<div class=\"c-calendar-instance__container\">\n    <div class=\"c-calendar-instance c-calendar-instance__film\">\n        <button class=\"c-calendar-instance__toggle\" id=\"c-calendar-instance__toggle-49546\" aria-controls=\"c-calendar-instance__info-49546\" aria-label=\"Find out More\"><span class=\"u-hidden-visually\">Find out More</span></button>\n        <div class=\"c-calendar-instance__content\">\n\n            <div data-tooltip >\n                <button class=\"c-calendar-instance__favourite instance\" data-eventid=\"49520\" data-instanceid=\"49546\" data-tooltip-trigger data-tooltip-content=\"Add to Schedule\" aria-label=\"Favourite Alipato At Muog (Flying Embers & A Fortress)\">\n                    <i class=\"far fa-plus\" aria-hidden=\"true\"></i>\n                    <span class=\"u-hidden-visually\">Favourite Alipato At Muog (Flying Embers & A Fortress)</span>\n                </button>\n            </div>\n\n            <h3 class=\"c-calendar-instance__title\">\n                Alipato At Muog (Flying Embers & A Fortress)            </h3>\n            <p class=\"c-calendar-instance__time\">\n                <time datetime=\"2026-06-14T13:30:00-07:00\">\n                    1:30 pm                </time>\n                                    <span class=\"c-calendar-instance__duration\"><span class=\"fal fa-clock\" aria-hidden=\"true\"></span> 106 min</span>\n                            </p>\n            <div class=\"c-calendar-instance__info\" id=\"c-calendar-instance__info-49546\" role=\"region\" aria-labelledby=\"c-calendar-instance__toggle-49546\">\n                                    <p class=\"c-calendar-instance__type\">Film</p>\n                                                    Burgos' impassioned documentary about the military abduction of his brother Jonas, an activist and organizer, and the subsequent cover-up, recently became only the second doc to win the Filipino Academy Award for Best Film.                \n                                    <div class=\"c-calendar-instance__buttons\">\n                                                                        <a class=\"c-event-instance__btn c-btn--small  c-btn c-btn--primary\" href=\"https://viff.org/whats-on/alipato-at-muog/book/qnFuk5vekh\">\n                                Book Now                            </a>\n                                                                <a class=\"c-event-instance__btn c-btn--small  c-btn c-btn--ghost\" href=\"https://viff.org/whats-on/alipato-at-muog/\">\n                        More Info\n                    </a>\n                    </div>\n                            </div>\n        </div>\n    </div>\n</div>\n",
    "moreInfo": "<p>Initially censored with an X-rating in its home country, <em>Alipato at Muog (Flying Embers and a Fortress)</em>, lives up to its national rating board\u2019s determination that it &#8220;undermine[s] the faith and confidence of the people in their government and/or duly-constituted authorities.&#8221;</p>\n<p>Burgos\u2019 impassioned documentary about his family\u2019s almost 20 year search for his brother Jonas, an organizer of peasant farmers who was abducted by state forces at a shopping mall in broad daylight in 2007, clarifies the irredeemable nature of the current system of Philippine government through a headstrong and wholehearted cinematic expression of love and rage.</p>\n<p>Burgos and his close-knit team recently managed to win the country\u2019s highest national film awards, becoming only the second documentary to be recognized as the Best Film of the year by the Filipino Academy.</p>\n<p>According to human rights group Karapatan, a total of 1,915 individuals have been documented as desaparecidos or victims of enforced disappearance from the martial law era under Ferdinand Marcos Sr. to the current administration of his son and namesake.</p>\n<blockquote><p>One of the most important national portraits of the decade.</p>\n<p><strong>Sinegang.ph, Best Filipino Films of 2024</strong></p></blockquote>\n",
    "eventType": "Film"
  },
  {
    "start": "2026-06-12T14:00:00",
    "end": "2026-06-12T15:37:00",
    "resourceId": "viff-centre-viff-cinema",
    "title": "<div class=\"c-calendar-instance__container\">\n    <div class=\"c-calendar-instance c-calendar-instance__film\">\n        <button class=\"c-calendar-instance__toggle\" id=\"c-calendar-instance__toggle-49533\" aria-controls=\"c-calendar-instance__info-49533\" aria-label=\"Find out More\"><span class=\"u-hidden-visually\">Find out More</span></button>\n        <div class=\"c-calendar-instance__content\">\n\n            <div data-tooltip >\n                <button class=\"c-calendar-instance__favourite instance\" data-eventid=\"49522\" data-instanceid=\"49533\" data-tooltip-trigger data-tooltip-content=\"Add to Schedule\" aria-label=\"Favourite Mistura\">\n                    <i class=\"far fa-plus\" aria-hidden=\"true\"></i>\n                    <span class=\"u-hidden-visually\">Favourite Mistura</span>\n                </button>\n            </div>\n\n            <h3 class=\"c-calendar-instance__title\">\n                Mistura            </h3>\n            <p class=\"c-calendar-instance__time\">\n                <time datetime=\"2026-06-12T14:00:00-07:00\">\n                    2:00 pm                </time>\n                                    <span class=\"c-calendar-instance__duration\"><span class=\"fal fa-clock\" aria-hidden=\"true\"></span> 97 min</span>\n                            </p>\n            <div class=\"c-calendar-instance__info\" id=\"c-calendar-instance__info-49533\" role=\"region\" aria-labelledby=\"c-calendar-instance__toggle-49533\">\n                                    <p class=\"c-calendar-instance__type\">Film</p>\n                                                    This foodie film from Peru tells the story of a newly single socialite reinventing herself \u2014 and the local cuisine \u2014 after her husband has left her for a younger woman. Along the way, she finds support from unexpected places...                \n                                    <div class=\"c-calendar-instance__buttons\">\n                                                                        <a class=\"c-event-instance__btn c-btn--small  c-btn c-btn--primary\" href=\"https://viff.org/whats-on/mistura/book/rE5QO3KXc5\">\n                                Book Now                            </a>\n                                                                <a class=\"c-event-instance__btn c-btn--small  c-btn c-btn--ghost\" href=\"https://viff.org/whats-on/mistura/\">\n                        More Info\n                    </a>\n                    </div>\n                            </div>\n        </div>\n    </div>\n</div>\n",
    "moreInfo": "<p>Lima, 1965. Wealthy socialite Norma (Barbara Mori) is devastated when her husband abandons her for a much younger woman. It\u2019s not long before the bank starts inquiring about the mortgage payments. Encouraged by her driver, Oscar (C\u00e9sar Ballumbrosio) to start a business doing something she loves, she elects to open a French restaurant in honour of her gastronome father, who was the French ambassador to Peru, and who passed on his love of French cooking. But it becomes clear that the restaurant is going to need to find something new, something more authentic, if it\u2019s going to get people excited.</p>\n<p>Ricardo de Montreuil\u2019s very satisfying film is itself classical in approach, even as it regales us with the advent of Peruvian cuisine, with its distinctive <em>mistura</em> (mixture) of local and far-flung influences. For Norma, adversity forces her to confront the confines of good taste she imbibed in childhood, with its attendant snobbery, sexism, colonialism and a side dish of hypocrisy. You will want to go out for a good meal afterwards \u2014 but there\u2019s plenty of food for thought here.</p>\n<blockquote><p>Masterful\u2026 a feast for the senses\u2026 a triumph of storytelling that transcends the \u2019food movie\u2019 genre.</p>\n<p><strong>Ricky Archuleta,<em> Film Threat</em></strong></p></blockquote>\n<blockquote><p>A visually stunning and heartfelt story of self-discovery and cultural appreciation that celebrates Peru\u2019s beauty, food, and people.</p>\n<p><strong>Roberto Tyler Ortiz, <em>Loud and Clear Reviews</em></strong></p></blockquote>\n",
    "eventType": "Film"
  },
  {
    "start": "2026-06-12T14:30:00",
    "end": "2026-06-12T16:02:00",
    "resourceId": "viff-centre-lochmaddy-studio-theatre",
    "title": "<div class=\"c-calendar-instance__container\">\n    <div class=\"c-calendar-instance c-calendar-instance__film\">\n        <button class=\"c-calendar-instance__toggle\" id=\"c-calendar-instance__toggle-49730\" aria-controls=\"c-calendar-instance__info-49730\" aria-label=\"Find out More\"><span class=\"u-hidden-visually\">Find out More</span></button>\n        <div class=\"c-calendar-instance__content\">\n\n            <div data-tooltip >\n                <button class=\"c-calendar-instance__favourite instance\" data-eventid=\"48730\" data-instanceid=\"49730\" data-tooltip-trigger data-tooltip-content=\"Add to Schedule\" aria-label=\"Favourite Departures\">\n                    <i class=\"far fa-plus\" aria-hidden=\"true\"></i>\n                    <span class=\"u-hidden-visually\">Favourite Departures</span>\n                </button>\n            </div>\n\n            <h3 class=\"c-calendar-instance__title\">\n                Departures            </h3>\n            <p class=\"c-calendar-instance__time\">\n                <time datetime=\"2026-06-12T14:30:00-07:00\">\n                    2:30 pm                </time>\n                                    <span class=\"c-calendar-instance__duration\"><span class=\"fal fa-clock\" aria-hidden=\"true\"></span> 92 min</span>\n                            </p>\n            <div class=\"c-calendar-instance__info\" id=\"c-calendar-instance__info-49730\" role=\"region\" aria-labelledby=\"c-calendar-instance__toggle-49730\">\n                                    <p class=\"c-calendar-instance__type\">Film</p>\n                                                    Two lads meet at an airport gate and begin monthly trips to Amsterdam together. Their chemistry is off the charts, but it's Jake who's calls the shots while Benji is the one who's emotionally invested. Comparisons to Pillion and Trainspotting are on mark.                \n                                    <div class=\"c-calendar-instance__buttons\">\n                                                                        <a class=\"c-event-instance__btn c-btn--small  c-btn c-btn--primary\" href=\"https://viff.org/whats-on/departures/book/K4J40DMj0k\">\n                                Book Now                            </a>\n                                                                <a class=\"c-event-instance__btn c-btn--small  c-btn c-btn--ghost\" href=\"https://viff.org/whats-on/departures/\">\n                        More Info\n                    </a>\n                    </div>\n                            </div>\n        </div>\n    </div>\n</div>\n",
    "moreInfo": "<p>&#8220;Inspired by all the dickheads that fucked us over,&#8221; according to the opening text, <em>Departures</em> is a gay rites-of-passage movie which leavens hard knocks with an almost jaunty sense of humour. UK critics have been quick to make comparisons with Danny Boyle\u2019s <em>Trainspotting</em>: it may be grim up North, but it only hurts when you laugh.</p>\n<p>Two lads \u2014 Benji and Jake \u2014 meet at an airport gate and begin monthly incognito trips to Amsterdam together. Their chemistry is off the charts, but it\u2019s Jake (David Tag) who\u2019s really calling the shots while Benji (writer and co-director Lloyd Eyre-Morgan) is the one who\u2019s emotionally invested. Unfolding in flashbacks, the movie doesn\u2019t shrink from BDSM, or physical and mental violence for that matter, but it still manages to be caring and compassionate. All in all, it makes for a strong companion piece to the recent <em>Pillion</em>.</p>\n<blockquote><p>A cult classic in the making.</p>\n<p><strong><em>Indiewire</em></strong></p></blockquote>\n<blockquote><p>A highly thoughtful exploration of love and identity. Though grappling with heavy issues such as body image, family rejection and toxic masculinity, <em>Departures</em> never veers into maudlin sentimentality, favouring instead dark comedy and a poppy visual style.</p>\n<p><strong>Phuong Le, <em>The Guardian</em></strong></p></blockquote>\n",
    "eventType": "Film"
  }
]
